setup.cfg
setup.py
edxcut/__init__.py
edxcut/course_tests.py
edxcut/course_unit_tester.py
edxcut/edxapi.py
edxcut/main.py
edxcut/make_tests.py
edxcut.egg-info/PKG-INFO
edxcut.egg-info/SOURCES.txt
edxcut.egg-info/dependency_links.txt
edxcut.egg-info/entry_points.txt
edxcut.egg-info/requires.txt
edxcut.egg-info/top_level.txt