Metadata-Version: 1.0
Name: edxcut
Version: 0.2
Summary: edX course unit tester
Home-page: http://pypi.python.org/pypi/edxcut/
Author: I. Chuang and G. Lopez
Author-email: ichuang@mit.edu
License: LICENSE.txt
Platform: UNKNOWN
